MANIFEST.in
README.md
pyproject.toml
setup.py
OASYS2_SYNED.egg-info/PKG-INFO
OASYS2_SYNED.egg-info/SOURCES.txt
OASYS2_SYNED.egg-info/dependency_links.txt
OASYS2_SYNED.egg-info/entry_points.txt
OASYS2_SYNED.egg-info/not-zip-safe
OASYS2_SYNED.egg-info/requires.txt
OASYS2_SYNED.egg-info/top_level.txt
orangecontrib/__init__.py
orangecontrib/syned/__init__.py
orangecontrib/syned/widgets/__init__.py
orangecontrib/syned/widgets/beamline_elements/__init__.py
orangecontrib/syned/widgets/beamline_elements/ow_beam_stopper.py
orangecontrib/syned/widgets/beamline_elements/ow_crystal.py
orangecontrib/syned/widgets/beamline_elements/ow_filter.py
orangecontrib/syned/widgets/beamline_elements/ow_grating.py
orangecontrib/syned/widgets/beamline_elements/ow_ideal_lens.py
orangecontrib/syned/widgets/beamline_elements/ow_mirror.py
orangecontrib/syned/widgets/beamline_elements/ow_screen.py
orangecontrib/syned/widgets/beamline_elements/ow_slits.py
orangecontrib/syned/widgets/beamline_elements/icons/beam_stopper.png
orangecontrib/syned/widgets/beamline_elements/icons/beamline_elements.png
orangecontrib/syned/widgets/beamline_elements/icons/crystal.png
orangecontrib/syned/widgets/beamline_elements/icons/filter.png
orangecontrib/syned/widgets/beamline_elements/icons/grating.png
orangecontrib/syned/widgets/beamline_elements/icons/ideal_lens.png
orangecontrib/syned/widgets/beamline_elements/icons/mirror.png
orangecontrib/syned/widgets/beamline_elements/icons/screen.png
orangecontrib/syned/widgets/beamline_elements/icons/slit.png
orangecontrib/syned/widgets/gui/__init__.py
orangecontrib/syned/widgets/gui/ow_insertion_device.py
orangecontrib/syned/widgets/gui/ow_light_source.py
orangecontrib/syned/widgets/gui/ow_optical_element.py
orangecontrib/syned/widgets/gui/misc/multiple_height_profile_simualtor_S.png
orangecontrib/syned/widgets/gui/misc/multiple_height_profile_simualtor_T.png
orangecontrib/syned/widgets/gui/misc/predabam_usage.png
orangecontrib/syned/widgets/light_sources/__init__.py
orangecontrib/syned/widgets/light_sources/ow_bm_light_source.py
orangecontrib/syned/widgets/light_sources/ow_undulator_light_source.py
orangecontrib/syned/widgets/light_sources/ow_wiggler_light_source.py
orangecontrib/syned/widgets/light_sources/icons/bm.png
