Metadata-Version: 2.4
Name: OASYS2-SYNED
Version: 1.0.5
Summary: SYNED SYNchrotron Elements Dictionary
Home-page: https://github.com/oasys-kit/OASYS2-SYNED
Download-URL: https://github.com/oasys-kit/OASYS2-SYNED
Author: Manuel Sanchez del Rio, Luca Rebuffi
Author-email: lrebuffi@anl.gov
License: GPLv3
Keywords: simulator,oasys2
Classifier: Development Status :: 4 - Beta
Classifier: Environment :: X11 Applications :: Qt
Classifier: Environment :: Console
Classifier: Environment :: Plugins
Classifier: Programming Language :: Python :: 3
Classifier: Intended Audience :: Science/Research
Requires-Dist: oasys2>=0.0.7
Requires-Dist: syned-gui-2>=1.0.3
Dynamic: author
Dynamic: author-email
Dynamic: classifier
Dynamic: description
Dynamic: download-url
Dynamic: home-page
Dynamic: keywords
Dynamic: license
Dynamic: requires-dist
Dynamic: summary
